README.txt
collective.privateurl-configure.zcml
setup.py
collective/__init__.py
collective.privateurl.egg-info/PKG-INFO
collective.privateurl.egg-info/SOURCES.txt
collective.privateurl.egg-info/dependency_links.txt
collective.privateurl.egg-info/entry_points.txt
collective.privateurl.egg-info/namespace_packages.txt
collective.privateurl.egg-info/not-zip-safe
collective.privateurl.egg-info/requires.txt
collective.privateurl.egg-info/top_level.txt
collective/privateurl/README.txt
collective/privateurl/__init__.py
collective/privateurl/configure.zcml
collective/privateurl/tests.py
collective/privateurl/viewlet.py
collective/privateurl/zope2.py
docs/HISTORY.txt