Metadata-Version: 1.0
Name: collective.privateurl
Version: 1.0
Summary: Completely block anonymous access on a Plone site
Home-page: https://svn.plone.org/svn/collective/collective.privateurl
Author: Roche Compaan
Author-email: roche@upfrontsystems.co.za
License: GPL
Platform: UNKNOWN
Classifier: Programming Language :: Python
Classifier: Topic :: Software Development :: Libraries :: Python Modules
Classifier: Framework :: Zope2
Classifier: Framework :: Plone
